huaweicloudsdkdevsecurity/__init__.py
huaweicloudsdkdevsecurity/v1/__init__.py
huaweicloudsdkdevsecurity/v1/devsecurity_async_client.py
huaweicloudsdkdevsecurity/v1/devsecurity_client.py
huaweicloudsdkdevsecurity/v1/model/__init__.py
huaweicloudsdkdevsecurity/v1/model/action_with_entities.py
huaweicloudsdkdevsecurity/v1/model/apk_component_info.py
huaweicloudsdkdevsecurity/v1/model/apk_component_item.py
huaweicloudsdkdevsecurity/v1/model/basic_info.py
huaweicloudsdkdevsecurity/v1/model/checker_rule.py
huaweicloudsdkdevsecurity/v1/model/create_sec_app_task_request.py
huaweicloudsdkdevsecurity/v1/model/create_sec_app_task_request_body.py
huaweicloudsdkdevsecurity/v1/model/create_sec_app_task_response.py
huaweicloudsdkdevsecurity/v1/model/delete_sec_app_task_request.py
huaweicloudsdkdevsecurity/v1/model/delete_sec_app_task_response.py
huaweicloudsdkdevsecurity/v1/model/hap_component_info.py
huaweicloudsdkdevsecurity/v1/model/hap_component_item.py
huaweicloudsdkdevsecurity/v1/model/operate_info_response_body.py
huaweicloudsdkdevsecurity/v1/model/permission_item.py
huaweicloudsdkdevsecurity/v1/model/privacy_compliance_info.py
huaweicloudsdkdevsecurity/v1/model/privacy_compliance_subtype.py
huaweicloudsdkdevsecurity/v1/model/show_sec_app_task_result_request.py
huaweicloudsdkdevsecurity/v1/model/show_sec_app_task_result_response.py
huaweicloudsdkdevsecurity/v1/model/show_sec_app_task_status_request.py
huaweicloudsdkdevsecurity/v1/model/show_sec_app_task_status_response.py
huaweicloudsdkdevsecurity/v1/model/vuln_info.py
huaweicloudsdkdevsecurity/v1/model/vuln_item.py
huaweicloudsdkdevsecurity/v1/model/vuln_rule.py
huaweicloudsdkdevsecurity/v1/region/__init__.py
huaweicloudsdkdevsecurity/v1/region/devsecurity_region.py
huaweicloudsdkdevsecurity-3.1.105.dist-info/LICENSE
huaweicloudsdkdevsecurity-3.1.105.dist-info/METADATA
huaweicloudsdkdevsecurity-3.1.105.dist-info/WHEEL
huaweicloudsdkdevsecurity-3.1.105.dist-info/top_level.txt
huaweicloudsdkdevsecurity-3.1.105.dist-info/RECORD
